Workbook
Name Taper_rate: 'DCF Model'!$C$21
Name Tax_rate: 'DCF Model'!$C$27:$C$27

Sheet DCF Model
B2: Discounted Cashflow Model
B3: Financial Modelling Course
B6: Company Overview
B7: Trent LTD is the Retal arm of the TATA Group, Operatng multiple retail formats
B9: WestSide- Depatrment Store chain 248 Stores
B10: Zudio- Value Fashion Retail Chain 766 stores
B11: Star Market- Hyper Market Format 78 Stores
B13: Total Store Count : 1000+ stores across 240+ Cities I Retail Area: ~13.6 Million Sqft
B16: Key Assumption And Methodology
B17: Parameter | C17: Value | D17: Rationale
B18: Valuation Date
B19: Projection Period
C20: 0.2 | D20: Based On management guidance
B21: Annual Growth Tapering | C21: 0.02
B23: Terminal Growth Rate | C23: 0.06 | D23: Conservative long term growth considering India's GDP and retail sector potential
B25: Risk Free Rate (RF) | C25: 0.065 | D25: India 10 year bond yield
B26: EquityRisk Premium (ERP) | C26: =12%-C25 -> 0.055 | D26: Exprcted return over RFR for equity investors
B27: Tax Rate | C27: 0.25 | D27: Effective Tax Rate based of historical performance
B30: Income Statement
B31: Particulars | C31: 44286 | D31: 44651 | E31: 45016 | F31: 45382 | G31: 45747 | H31: CAGR
B32: Sales | C32: ='Data Sheet'!F17 -> 2592.96 | D32: ='Data Sheet'!G17 -> 4498.02 | E32: ='Data Sheet'!H17 -> 8242.02 | F32: ='Data Sheet'!I17 -> 12375.11 | G32: ='Data Sheet'!J17 -> 17134.61
B33: % Of growth | D33: =D32/C32-1 -> 0.73470474 | E33: =E32/D32-1 -> 0.83236624 | F33: =F32/E32-1 -> 0.50146566 | G33: =G32/F32-1 -> 0.38460264 | H33: =_xlfn.RRI(4,C32,G32) -> 0.60331775
B34: COGS | C34: =SUM('Data Sheet'!F18,-'Data Sheet'!F19,'Data Sheet'!F20:F21) -> 1675.41 | D34: =SUM('Data Sheet'!G18,-'Data Sheet'!G19,'Data Sheet'!G20:G21) -> 2680.57 | E34: =SUM('Data Sheet'!H18,-'Data Sheet'!H19,'Data Sheet'!H20:H21) -> 5076.01 | F34: =SUM('Data Sheet'!I18,-'Data Sheet'!I19,'Data Sheet'!I20:I21) -> 7452.64 | G34: =SUM('Data Sheet'!J18,-'Data Sheet'!J19,'Data Sheet'!J20:J21) -> 10408.8
B35: % of Revenue | C35: =C34/C32 -> 0.646138 | D35: =D34/D32 -> 0.59594444 | E35: =E34/E32 -> 0.61586965 | F35: =F34/F32 -> 0.60222818 | G35: =G34/G32 -> 0.60747224
B36: Gross Profit | C36: =C32-C34 -> 917.55 | D36: =D32-D34 -> 1817.45 | E36: =E32-E34 -> 3166.01 | F36: =F32-F34 -> 4922.47 | G36: =G32-G34 -> 6725.81
B37: % Margin | C37: =C36/C32 -> 0.353862 | D37: =D36/D32 -> 0.40405556 | E37: =E36/E32 -> 0.38413035 | F37: =F36/F32 -> 0.39777182 | G37: =G36/G32 -> 0.39252776
B38: Operating Expenses | C38: =SUM('Data Sheet'!F22:F24) -> 803.68 | D38: =SUM('Data Sheet'!G22:G24) -> 1222.73 | E38: =SUM('Data Sheet'!H22:H24) -> 2051.86 | F38: =SUM('Data Sheet'!I22:I24) -> 2951.78 | G38: =SUM('Data Sheet'!J22:J24) -> 3905.85
B39: % Revenue | C39: =C38/C32 -> 0.30994693 | D39: =D38/D32 -> 0.27183739 | E39: =E38/E32 -> 0.24895111 | F39: =F38/F32 -> 0.23852556 | G39: =G38/G32 -> 0.22795091
B40: EBITDA | C40: =C36-C38 -> 113.87 | D40: =D36-D38 -> 594.72 | E40: =E36-E38 -> 1114.15 | F40: =F36-F38 -> 1970.69 | G40: =G36-G38 -> 2819.96
B41: % Margin | C41: =C40/C32 -> 0.043915062 | D41: =D40/D32 -> 0.13221818 | E41: =E40/E32 -> 0.13517924 | F41: =F40/F32 -> 0.15924626 | G41: =G40/G32 -> 0.16457684
B42: Depreciation | C42: ='Data Sheet'!F26 -> 257.3 | D42: ='Data Sheet'!G26 -> 310.82 | E42: ='Data Sheet'!H26 -> 493.69 | F42: ='Data Sheet'!I26 -> 671.11 | G42: ='Data Sheet'!J26 -> 895.18
B43: % Of Sales | C43: =C42/C32 -> 0.099230223 | D43: =D42/D32 -> 0.069101516 | E43: =E42/E32 -> 0.059899151 | F43: =F42/F32 -> 0.054230629 | G43: =G42/G32 -> 0.052243967
B44: EBIT | C44: =C40-C42 -> -143.43 | D44: =D40-D42 -> 283.9 | E44: =E40-E42 -> 620.46 | F44: =F40-F42 -> 1299.58 | G44: =G40-G42 -> 1924.78
B45: % Margin | C45: =C44/C32 -> -0.055315161 | D45: =D44/D32 -> 0.06311666 | E45: =E44/E32 -> 0.075280089 | F45: =F44/F32 -> 0.10501563 | G45: =G44/G32 -> 0.11233287
B46: Other Income | C46: ='Data Sheet'!F25 -> 199.4 | D46: ='Data Sheet'!G25 -> 152.16 | E46: ='Data Sheet'!H25 -> 340.6 | F46: ='Data Sheet'!I25 -> 988.91 | G46: ='Data Sheet'!J25 -> 305.06
B47: Interest | C47: ='Data Sheet'!F27 -> 260.79 | D47: ='Data Sheet'!G27 -> 324.84 | E47: ='Data Sheet'!H27 -> 408.99 | F47: ='Data Sheet'!I27 -> 367.66 | G47: ='Data Sheet'!J27 -> 200.1
B48: % debt | C48: =C47/'Data Sheet'!F59 -> 0.087996815 | D48: =D47/'Data Sheet'!G59 -> 0.068743969 | E48: =E47/'Data Sheet'!H59 -> 0.09161675 | F48: =F47/'Data Sheet'!I59 -> 0.20973308 | G48: =G47/'Data Sheet'!J59 -> 0.08944256
B49: Profit Before Tax | C49: =C44+C46-C47 -> -204.82 | D49: =D44+D46-D47 -> 111.22 | E49: =E44+E46-E47 -> 552.07 | F49: =F44+F46-F47 -> 1920.83 | G49: =G44+G46-G47 -> 2029.74
B50: % of Revenue | C50: =C49/C32 -> -0.078990806 | D50: =D49/D32 -> 0.024726435 | E50: =E49/E32 -> 0.066982366 | F50: =F49/F32 -> 0.15521721 | G50: =G49/G32 -> 0.11845849
B51: Tax | C51: ='Data Sheet'!F29 -> -23.69 | D51: ='Data Sheet'!G29 -> 76.62 | E51: ='Data Sheet'!H29 -> 158.44 | F51: ='Data Sheet'!I29 -> 443.37 | G51: ='Data Sheet'!J29 -> 495.33
B52: % of PBT | C52: =C51/C49 -> 0.11566253 | D52: =D51/D49 -> 0.68890487 | E52: =E51/E49 -> 0.28699259 | F52: =F51/F49 -> 0.23082209 | G52: =G51/G49 -> 0.24403618
B53: Net Profit | C53: =C49-C51 -> -181.13 | D53: =D49-D51 -> 34.6 | E53: =E49-E51 -> 393.63 | F53: =F49-F51 -> 1477.46 | G53: =G49-G51 -> 1534.41
B54: % of revenue | C54: =C53/C32 -> -0.069854529 | D54: =D53/D32 -> 0.0076922735 | E54: =E53/E32 -> 0.047758923 | F54: =F53/F32 -> 0.11938965 | G54: =G53/G32 -> 0.089550331
B56: Balance Sheet
B57: Particulars | C57: 44286 | D57: 44651 | E57: 45016 | F57: 45382 | G57: 45747
B58: Equity Share capital | C58: ='Data Sheet'!F57 -> 35.55 | D58: ='Data Sheet'!G57 -> 35.55 | E58: ='Data Sheet'!H57 -> 35.55 | F58: ='Data Sheet'!I57 -> 35.55 | G58: ='Data Sheet'!J57 -> 35.55
B59: Reserves | C59: ='Data Sheet'!F58 -> 2277.48 | D59: ='Data Sheet'!G58 -> 2328.45 | E59: ='Data Sheet'!H58 -> 2559.94 | F59: ='Data Sheet'!I58 -> 4032.19 | G59: ='Data Sheet'!J58 -> 5426.19
B60: Borrowings | C60: ='Data Sheet'!F59 -> 2963.63 | D60: ='Data Sheet'!G59 -> 4725.36 | E60: ='Data Sheet'!H59 -> 4464.14 | F60: ='Data Sheet'!I59 -> 1752.99 | G60: ='Data Sheet'!J59 -> 2237.19
B61: Other Liabilities | C61: ='Data Sheet'!F60 -> 447.07 | D61: ='Data Sheet'!G60 -> 636.66 | E61: ='Data Sheet'!H60 -> 1021.9 | F61: ='Data Sheet'!I60 -> 1341.02 | G61: ='Data Sheet'!J60 -> 1720.71
B62: Total | C62: =SUM(C58:C61) -> 5723.73 | D62: =SUM(D58:D61) -> 7726.02 | E62: =SUM(E58:E61) -> 8081.53 | F62: =SUM(F58:F61) -> 7161.75 | G62: =SUM(G58:G61) -> 9419.64
B63: Net Block | C63: ='Data Sheet'!F62 -> 3053.82 | D63: ='Data Sheet'!G62 -> 4686.71 | E63: ='Data Sheet'!H62 -> 4526.95 | F63: ='Data Sheet'!I62 -> 2449.92 | G63: ='Data Sheet'!J62 -> 3895.13
B64: Capital Work in Progress | C64: ='Data Sheet'!F63 -> 107.98 | D64: ='Data Sheet'!G63 -> 104.72 | E64: ='Data Sheet'!H63 -> 101.72 | F64: ='Data Sheet'!I63 -> 223.78 | G64: ='Data Sheet'!J63 -> 179.5
B65: Investments | C65: ='Data Sheet'!F64 -> 1487.29 | D65: ='Data Sheet'!G64 -> 1283.72 | E65: ='Data Sheet'!H64 -> 1109.87 | F65: ='Data Sheet'!I64 -> 1416.03 | G65: ='Data Sheet'!J64 -> 1480.25
B66: Other Assets | C66: ='Data Sheet'!F67 -> 20.77 | D66: ='Data Sheet'!G67 -> 18.26 | E66: ='Data Sheet'!H67 -> 34.39 | F66: ='Data Sheet'!I67 -> 81.74 | G66: ='Data Sheet'!J67 -> 62.95
B67: Inventory | C67: ='Data Sheet'!F68 -> 428.39 | D67: ='Data Sheet'!G68 -> 867.78 | E67: ='Data Sheet'!H68 -> 1361.16 | F67: ='Data Sheet'!I68 -> 1582.73 | G67: ='Data Sheet'!J68 -> 2045.05
B68: Cash & Bank | C68: ='Data Sheet'!F69 -> 81.47 | D68: ='Data Sheet'!G69 -> 85.97 | E68: ='Data Sheet'!H69 -> 86.3 | F68: ='Data Sheet'!I69 -> 297.56 | G68: ='Data Sheet'!J69 -> 339.84
B69: Other Assets | C69: ='Data Sheet'!F65-SUM('Data Sheet'!F67:F69) -> 544.01 | D69: ='Data Sheet'!G65-SUM('Data Sheet'!G67:G69) -> 678.86 | E69: ='Data Sheet'!H65-SUM('Data Sheet'!H67:H69) -> 861.14 | F69: ='Data Sheet'!I65-SUM('Data Sheet'!I67:I69) -> 1109.99 | G69: ='Data Sheet'!J65-SUM('Data Sheet'!J67:J69) -> 1416.92
B70: Total | C70: =SUM(C63:C69) -> 5723.73 | D70: =SUM(D63:D69) -> 7726.02 | E70: =SUM(E63:E69) -> 8081.53 | F70: =SUM(F63:F69) -> 7161.75 | G70: =SUM(G63:G69) -> 9419.64
B72: Revenue Projections And Growth Assumptions
B73: Year | C73: FY 2026 | D73: FY 2027 | E73: FY 2028 | F73: FY 2029 | G73: FY 2030
B74: Revenue Growth% | C74: {=CHOOSE(D76,C77:G77,C78:G78,C79:G79)} -> 0.2 | D74: 0.18 | E74: 0.16 | F74: 0.14 | G74: 0.12
B75: Revenue in (Crs) | C75: =G32*(1+C74) -> 20561.532 | D75: =C75*(1+D74) -> 24262.608 | E75: =D75*(1+E74) -> 28144.625 | F75: =E75*(1+F74) -> 32084.873 | G75: =F75*(1+G74) -> 35935.057
B76: Chosen Scenarios | C76: Base Case | D76: =MATCH(C76,B77:B79) -> 1
B77: Base Case | C77: =C20 -> 0.2 | D77: =C77-Taper_rate -> 0.18 | E77: =D77-Taper_rate -> 0.16 | F77: =E77-Taper_rate -> 0.14 | G77: =F77-Taper_rate -> 0.12
B78: Best Case | C78: =C77+5% -> 0.25 | D78: =C78-Taper_rate -> 0.23 | E78: =D78-Taper_rate -> 0.21 | F78: =E78-Taper_rate -> 0.19 | G78: =F78-Taper_rate -> 0.17
B79: Worst Case | C79: =C77-5% -> 0.15 | D79: =C79-Taper_rate -> 0.13 | E79: =D79-Taper_rate -> 0.11 | F79: =E79-Taper_rate -> 0.09 | G79: =F79-Taper_rate -> 0.07
B82: Free Cash flow Projection (Rs Crs)
C83: FY 2026 | D83: FY 2027 | E83: FY 2028 | F83: FY 2029 | G83: FY 2030
B84: Revenue | C84: =C75 -> 20561.532 | D84: =D75 -> 24262.608 | E84: =E75 -> 28144.625 | F84: =F75 -> 32084.873 | G84: =G75 -> 35935.057
B85: EBITDA Margin% | C85: =G41 -> 0.16457684 | D85: =C85 -> 0.16457684 | E85: =D85 -> 0.16457684 | F85: =E85 -> 0.16457684 | G85: =F85 -> 0.16457684
B86: EBITDA | C86: =C84*C85 -> 3383.952 | D86: =D84*D85 -> 3993.0634 | E86: =E84*E85 -> 4631.9535 | F86: =F84*F85 -> 5280.427 | G86: =G84*G85 -> 5914.0782
B87: Less Depreciation | C87: =C84*AVERAGE($C$43:$G$43) -> 1376.4115 | D87: =D84*AVERAGE($C$43:$G$43) -> 1624.1656 | E87: =E84*AVERAGE($C$43:$G$43) -> 1884.0321 | F87: =F84*AVERAGE($C$43:$G$43) -> 2147.7966 | G87: =G84*AVERAGE($C$43:$G$43) -> 2405.5322
B88: EBIT | C88: =C86-C87 -> 2007.5405 | D88: =D86-D87 -> 2368.8978 | E88: =E86-E87 -> 2747.9214 | F88: =F86-F87 -> 3132.6304 | G88: =G86-G87 -> 3508.5461
B89: Less Tax | C89: {=C88*Tax_rate} -> 501.88512 | D89: {=D88*Tax_rate} -> 592.22444 | E89: {=E88*Tax_rate} -> 686.98035 | F89: {=F88*Tax_rate} -> 783.1576 | G89: {=G88*Tax_rate} -> 877.13652
B90: NOPAT | C90: =C88-C89 -> 1505.6554 | D90: =D88-D89 -> 1776.6733 | E90: =E88-E89 -> 2060.9411 | F90: =F88-F89 -> 2349.4728 | G90: =G88-G89 -> 2631.4096
B91: Add: Depreciation | C91: =C87 -> 1376.4115 | D91: =D87 -> 1624.1656 | E91: =E87 -> 1884.0321 | F91: =F87 -> 2147.7966 | G91: =G87 -> 2405.5322
B92: Less: Reinvestment | C92: =C90*-50% -> -752.82768 | D92: =D90*-50% -> -888.33667 | E92: =E90*-50% -> -1030.4705 | F92: =F90*-50% -> -1174.7364 | G92: =G90*-50% -> -1315.7048
B93: Free Cash flow to firm | C93: =SUM(C90:C92) -> 2129.2392 | D93: =SUM(D90:D92) -> 2512.5023 | E93: =SUM(E90:E92) -> 2914.5026 | F93: =SUM(F90:F92) -> 3322.533 | G93: =SUM(G90:G92) -> 3721.2369
B95: WACC Calculation
B97: Target Capital Structure
B98: Proportion Of Debt | C98: =Comps!G21 -> 0.071924563
B99: Proportion Of Equity | C99: =1-C98 -> 0.92807544
B100: Current Capital Structure
B101: Market Cap | C101: =Comps!E7 -> 160446.92
B102: Tota Debt | C102: =Comps!F7 -> 2561.25
B103: Debt/Equity | C103: =C102/C101 -> 0.015963223
B104: Cost Of Debt
B105: Pre-tax cost of debt | C105: 0.07
B106: tax Rate | C106: {=Tax_rate} -> 0.25
B107: After Tax Cost of Debt | C107: =C105*(1-C106) -> 0.0525
B108: Cost Of Equity
B109: Risk Free Rate | C109: =C25 -> 0.065
B110: Equity Risk Premium | C110: =C26 -> 0.055
B111: Levered Equity Beta | C111: {=Comps!J21*(1+'DCF Model'!C103*(1-Tax_rate))} -> 0.49496193
B112: Cost Of Equity | C112: =C109+C111*C110 -> 0.092222906
B113: WACC | C113: =(C112*C99)+(C107*C98) -> 0.089365854
B115: Terminal Value
B117: Terminal Year FCF (Fy30) | C117: =G93 -> 3721.2369
B118: Terminal Growth Rate | C118: =C23 -> 0.06
B119: Terminal Value = FCF*(1+G) / (WACC-G)
...

Sheet Comps
C4: Comps Data
C6: Name | D6: CMP Rs. | E6: Mar Cap Rs.Cr. | F6: Debt Rs.Cr. | G6: Debt / Eq | H6: Sales Rs.Cr. | I6: Beta | J6: Cash and Equivalent
C7: Trent | D7: 3008.95 | E7: 160446.92 | F7: 2561.25 | G7: 0.37 | H7: 20945.44 | I7: 0.79 | J7: 283
C8: Lenskart Solut. | D8: 589.95 | E8: 102575.81 | F8: 3096.6 | G8: 0.35 | H8: 8814.04 | I8: 0.63 | J8: 1543.68
C9: Vedant Fashions | D9: 522 | E9: 12683.46 | F9: 457.59 | G9: 0.23 | H9: 1455.66 | I9: 0.92 | J9: 11.09
C10: A B Lifestyle | D10: 91.48 | E10: 11165.34 | F10: 3018.1 | G10: 2.14 | H10: 8600.97 | I10: 0.88 | J10: 91.51
C11: V2 Retail | D11: 222.9 | E11: 8127.77 | F11: 994.59 | G11: 1.1 | H11: 3060.03 | I11: 0.55 | J11: 128.65
C13: Industry Beta
C15: Name | D15: Equit Value | E15: Total Debt | F15: Debt/Equity | G15: Debt /Capital | H15: Tax Rate % | I15: Levered Beta | J15: Unlivered Beta
C16: Lenskart Solut. | D16: =E8 -> 102575.81 | E16: =F8 -> 3096.6 | F16: =E16/D16 -> 0.030188404 | G16: =E16/(D16+E16) -> 0.02930377 | H16: {=Tax_rate} -> 0.25 | I16: =I8 -> 0.63 | J16: =I16/(1+F16)*(1-H16) -> 0.45865397
C17: Vedant Fashions | D17: =E9 -> 12683.46 | E17: =F9 -> 457.59 | F17: =E17/D17 -> 0.036077695 | G17: =E17/(D17+E17) -> 0.034821418 | H17: {=Tax_rate} -> 0.25 | I17: =I9 -> 0.92 | J17: =I17/(1+F17)*(1-H17) -> 0.66597322
C18: A B Lifestyle | D18: =E10 -> 11165.34 | E18: =F10 -> 3018.1 | F18: =E18/D18 -> 0.27030973 | G18: =E18/(D18+E18) -> 0.21279041 | H18: {=Tax_rate} -> 0.25 | I18: =I10 -> 0.88 | J18: =I18/(1+F18)*(1-H18) -> 0.51955833
C19: V2 Retail | D19: =E11 -> 8127.77 | E19: =F11 -> 994.59 | F19: =E19/D19 -> 0.12236936 | G19: =E19/(D19+E19) -> 0.10902771 | H19: {=Tax_rate} -> 0.25 | I19: =I11 -> 0.55 | J19: =I19/(1+F19)*(1-H19) -> 0.36752607
C20: Average | F20: =AVERAGE(F16:F19) -> 0.1147363 | G20: =AVERAGE(G16:G19) -> 0.096485826 | H20: =AVERAGE(H16:H19) -> 0.25 | I20: =AVERAGE(I16:I19) -> 0.745 | J20: =AVERAGE(J16:J19) -> 0.5029279
C21: Median | F21: =MEDIAN(F16:F19) -> 0.079223527 | G21: =MEDIAN(G16:G19) -> 0.071924563 | H21: =MEDIAN(H16:H19) -> 0.25 | I21: =MEDIAN(I16:I19) -> 0.755 | J21: =MEDIAN(J16:J19) -> 0.48910615
C23: Name | D23: CMP ₹ | E23: Mar Cap ₹ Cr | F23: Debt ₹ Cr | G23: Debt / Eq | H23: Sales ₹ Cr | I23: Beta | J23: Cash & Equivalents ₹ Cr
C24: SBI | D24: 1005.9 | E24: 927686.13 | F24: 6894110.9 | G24: 11.08 | H24: 136240.49 | I24: 1.05 | J24: 212013.35
C25: Union Bank | D25: 186 | E25: 142404.91 | F25: 1370000 | G25: 9.74 | H25: 27427.1 | I25: 1.42 | J25: 43255.93
C26: Punjab National Bank | D26: 116.45 | E26: 133835.31 | F26: 1843390.4 | G26: 11.79 | H26: 33589.17 | I26: 1.24 | J26: 71273.23
C27: Bank of Baroda | D27: 237 | E27: 122458.81 | F27: 1835226.4 | G27: 10.89 | H27: 35114.52 | I27: 1.26 | J27: 50665.14
C28: Indian Bank | D28: 859.9 | E28: 115792.14 | F28: 1230000 | G28: 10.64 | H28: 18095.14 | I28: 1.33 | J28: 31796

Sheet Data Sheet
A1: COMPANY NAME | B1: TRENT LTD | E1: =IF(B2<>B3, "A NEW VERSION OF THE WORKSHEET IS AVAILABLE", "")
A2: LATEST VERSION | B2: 2.1 | E2: PLEASE DO NOT MAKE ANY CHANGES TO THIS SHEET
A3: CURRENT VERSION | B3: 2.1
B4: ='[1]Data Sheet'!B1&" -" -> TRENT LTD -
A5: META
A6: Number of shares | B6: =IF(B9>0, B9/B8, 0) -> 53.32323
A7: Face Value | B7: 1
A8: Current Price | B8: 2997 | C8: =IFERROR('[1]Data Sheet'!C18,'[1]Data Sheet'!C20:C22)*-1 -> -1070.02
A9: Market Capitalization | B9: 159809.72
A15: PROFIT & LOSS
A16: Report Date | B16: 42825 | C16: 43190 | D16: 43555 | E16: 43921 | F16: 44286 | G16: 44651 | H16: 45016 | I16: 45382 | J16: 45747
A17: Sales | B17: 1812.44 | C17: 2157.46 | D17: 2630.24 | E17: 3485.98 | F17: 2592.96 | G17: 4498.02 | H17: 8242.02 | I17: 12375.11 | J17: 17134.61
A18: Raw Material Cost | B18: 911.22 | C18: 1070.02 | D18: 1459.67 | E18: 1951.64 | F18: 1371.64 | G18: 2920.38 | H18: 5211.05 | I18: 7123.6 | J18: 10143.39
A19: Change in Inventory | B19: 29.86 | C19: 38.51 | D19: 148.23 | E19: 69.89 | F19: -162.36 | G19: 438.84 | H19: 491.31 | I19: 164.71 | J19: 454.25
A20: Power and Fuel | B20: 51.28 | C20: 52.75 | D20: 59.18 | E20: 66.64 | F20: 49.41 | G20: 71.89 | H20: 144.28 | I20: 229.16 | J20: 349.87
A21: Other Mfr. Exp | B21: 81.91 | C21: 90.78 | D21: 122.09 | E21: 97.51 | F21: 92 | G21: 127.14 | H21: 211.99 | I21: 264.59 | J21: 369.79
A22: Employee Cost | B22: 194.72 | C22: 233.02 | D22: 288.89 | E22: 361.01 | F22: 303.4 | G22: 402.92 | H22: 659.07 | I22: 1041.74 | J22: 1315.54
A23: Selling and admin | B23: 407.07 | C23: =SUM('Data Sheet'!F18) -> 1371.64 | D23: 514.41 | E23: 436.82 | F23: 364.62 | G23: 705.03 | H23: 1252.53 | I23: 1709.55 | J23: 2322.83
A24: Other Expenses | B24: 62.57 | C24: 90.29 | D24: 93.59 | E24: 113.28 | F24: 135.66 | G24: 114.78 | H24: 140.26 | I24: 200.49 | J24: 267.48
A25: Other Income | B25: 81.31 | C25: 27.47 | D25: 30.14 | E25: 146.63 | F25: 199.4 | G25: 152.16 | H25: 340.6 | I25: 988.91 | J25: 305.06
A26: Depreciation | B26: 41.29 | C26: 45.53 | D26: 51.67 | E26: 247.24 | F26: 257.3 | G26: 310.82 | H26: 493.69 | I26: 671.11 | J26: 895.18
A27: Interest | B27: 45.55 | C27: 43.78 | D27: 50.64 | E27: 263.37 | F27: 260.79 | G27: 324.84 | H27: 408.99 | I27: 367.66 | J27: 200.1
A28: Profit before tax | B28: 128 | C28: 146.66 | D28: 168.47 | E28: 164.99 | F28: -204.82 | G28: 111.22 | H28: 552.07 | I28: 1920.83 | J28: 2029.74
A29: Tax | B29: 43.05 | C29: 59.62 | D29: 73.61 | E29: 59.01 | F29: -23.69 | G29: 76.62 | H29: 158.44 | I29: 443.37 | J29: 495.33
A30: Net profit | B30: 84.86 | C30: 86.97 | D30: 96.96 | E30: 122.85 | F30: -146.17 | G30: 105.83 | H30: 444.63 | I30: 1486.8 | J30: 1546.72
A31: Dividend Amount | B31: 33.23 | C31: 38.21 | D31: 43.2 | E31: 35.55 | F31: 21.33 | G31: 60.44 | H31: 78.21 | I31: 113.76 | J31: 177.75
A40: Quarters
A41: Report Date | B41: 45382 | C41: 45473 | D41: 45565 | E41: 45657 | F41: 45747 | G41: 45838 | H41: 45930 | I41: 46022 | J41: 46112
A42: Sales | B42: 3297.7 | C42: 4104.44 | D42: 4156.67 | E42: 4656.56 | F42: 4216.94 | G42: 4883.48 | H42: 4817.68 | I42: 5345.06 | J42: 5027.99
A43: Expenses | B43: 2828.06 | C43: 3491.09 | D43: 3510.95 | E43: 3809.19 | F43: 3566.03 | G43: 4035.62 | H43: 4001.7 | I43: 4263.99 | J43: 4116.69
A44: Other Income | B44: 694.87 | C44: 100.91 | D44: 51.04 | E44: 79.87 | F44: 74.34 | G44: 49.8 | H44: 27.55 | I44: 4.55 | J44: 27.91
A45: Depreciation | B45: 212.94 | C45: 181.32 | D45: 196.95 | E45: 244.93 | F45: 271.98 | G45: 292.93 | H45: 324.93 | I45: 366.74 | J45: 376.59
A46: Interest | B46: 32.54 | C46: 31.55 | D46: 33 | E46: 36.52 | F46: 37.52 | G46: 40.04 | H46: 41.62 | I46: 42.94 | J46: 43.75
A47: Profit before tax | B47: 919.03 | C47: 501.39 | D47: 466.81 | E47: 645.79 | F47: 415.75 | G47: 564.69 | H47: 476.98 | I47: 675.94 | J47: 518.87
A48: Tax | B48: 206.94 | C48: 110.18 | D48: 131.75 | E48: 149.25 | F48: 104.15 | G48: 139.99 | H48: 103.56 | I48: 165.83 | J48: 105.77
A49: Net profit | B49: 704.23 | C49: 392.57 | D49: 338.75 | E49: 497.25 | F49: 318.15 | G49: 429.69 | H49: 376.86 | I49: 512.77 | J49: 400.33
A50: Operating Profit | B50: 469.64 | C50: 613.35 | D50: 645.72 | E50: 847.37 | F50: 650.91 | G50: 847.86 | H50: 815.98 | I50: 1081.07 | J50: 911.3
A51: EBITDA | B51: 16892.02 | C51: 20164.6 | D51: 19850 | E51: 20404 | F51: 22268 | G51: 23828 | H51: 22359 | I51: 18164 | J51: 17822
A55: BALANCE SHEET
A56: Report Date | B56: 42825 | C56: 43190 | D56: 43555 | E56: 43921 | F56: 44286 | G56: 44651 | H56: 45016 | I56: 45382 | J56: 45747
A57: Equity Share Capital | B57: 33.23 | C57: 33.23 | D57: 33.23 | E57: 35.55 | F57: 35.55 | G57: 35.55 | H57: 35.55 | I57: 35.55 | J57: 35.55
A58: Reserves | B58: 1514.46 | C58: 1562.14 | D58: 1613.28 | E58: 2352.22 | F58: 2277.48 | G58: 2328.45 | H58: 2559.94 | I58: 4032.19 | J58: 5426.19
A59: Borrowings | B59: 391.74 | C59: 391.43 | D59: 494.14 | E59: 299.74 | F59: 2963.63 | G59: 4725.36 | H59: 4464.14 | I59: 1752.99 | J59: 2237.19
A60: Other Liabilities | B60: 282.82 | C60: 349.06 | D60: 418.11 | E60: 2819.17 | F60: 447.07 | G60: 636.66 | H60: 1021.9 | I60: 1341.02 | J60: 1720.71
A61: Total | B61: 2222.25 | C61: 2335.86 | D61: 2558.76 | E61: 5506.68 | F61: 5723.73 | G61: 7726.02 | H61: 8081.53 | I61: 7161.75 | J61: 9419.64
A62: Net Block | B62: 548.71 | C62: 612.53 | D62: 662.18 | E62: 2738.43 | F62: 3053.82 | G62: 4686.71 | H62: 4526.95 | I62: 2449.92 | J62: 3895.13
A63: Capital Work in Progress | B63: 5.48 | C63: 9.59 | D63: 87.18 | E63: 23.32 | F63: 107.98 | G63: 104.72 | H63: 101.72 | I63: 223.78 | J63: 179.5
A64: Investments | B64: 1079.96 | C64: 1022.88 | D64: 882.83 | E64: 1514.78 | F64: 1487.29 | G64: 1283.72 | H64: 1109.87 | I64: 1416.03 | J64: 1480.25
A65: Other Assets | B65: 588.1 | C65: 690.86 | D65: 926.57 | E65: 1230.15 | F65: 1074.64 | G65: 1650.87 | H65: 2342.99 | I65: 3072.02 | J65: 3864.76
A66: Total | B66: 2222.25 | C66: 2335.86 | D66: 2558.76 | E66: 5506.68 | F66: 5723.73 | G66: 7726.02 | H66: 8081.53 | I66: 7161.75 | J66: 9419.64
A67: Receivables | B67: 5.92 | C67: 15.1 | D67: 16.54 | E67: 17.12 | F67: 20.77 | G67: 18.26 | H67: 34.39 | I67: 81.74 | J67: 62.95
... A70: No. of Equity Shares | B70: 332316730 | C70: 332316730 | D70: 332316730 | E70: 355487461 | F70: 355487461 | G70: 355487461 | H70: 355487461 | I70: 355487461 | J70: 355487461
A71: New Bonus Shares
A72: Face value | B72: 1 | C72: 1 | D72: 1 | E72: 1 | F72: 1 | G72: 1 | H72: 1 | I72: 1 | J72: 1
A80: CASH FLOW:
A81: Report Date | B81: 42825 | C81: 43190 | D81: 43555 | E81: 43921 | F81: 44286 | G81: 44651 | H81: 45016 | I81: 45382 | J81: 45747
A82: Cash from Operating Activity | B82: 102.44 | C82: 76.86 | D82: 20.98 | E82: 361.16 | F82: 285.03 | G82: 58.08 | H82: 594.88 | I82: 1348.98 | J82: 1660.9
A83: Cash from Investing Activity | B83: -43.7 | C83: -4.02 | D83: -37.03 | E83: -808.56 | F83: 17.71 | G83: 56.03 | H83: -102.63 | I83: -508.21 | J83: -923.31
A84: Cash from Financing Activity | B84: -51.36 | C84: -74.31 | D84: 37.47 | E84: 451.94 | F84: -283.11 | G84: -107.98 | H84: -491.41 | I84: -629.45 | J84: -693.67
A85: Net Cash Flow | B85: 7.38 | C85: -1.47 | D85: 21.42 | E85: 4.54 | F85: 19.63 | G85: 6.13 | H85: 0.84 | I85: 211.32 | J85: 43.92
H86: =SUM(G67:G68)-SUM(H67:H68) -> -509.51 | I86: =SUM(H67:H68)-SUM(I67:I68) -> -268.92 | J86: =SUM(I67:I68)-SUM(J67:J68) -> -443.53
H87: =H86+H83 -> -612.14 | I87: =I86+I83 -> -777.13 | J87: =J86+J83 -> -1366.84
A88: NOPAT | H88: {='DCF Model'!E44*(1-Tax_rate)} -> 465.345 | I88: {='DCF Model'!F44*(1-Tax_rate)} -> 974.685 | J88: {='DCF Model'!G44*(1-Tax_rate)} -> 1443.585
H89: =H87/H88 -> -1.3154541 | I89: =I87/I88 -> -0.797314 | J89: =J87/J88 -> -0.94683721
A91: PRICE: | B91: 177.8 | C91: 230.03 | D91: 241.27 | E91: 322.9 | F91: 500.7 | G91: 850.33 | H91: 916.63 | I91: 2632 | J91: 3550.1
A93: DERIVED:
A94: Adjusted Equity Shares in Cr | B94: 49.85 | C94: 49.85 | D94: 49.85 | E94: 53.32 | F94: 53.32 | G94: 53.32 | H94: 53.32 | I94: 53.32 | J94: 53.32
