Workbook
Name Beta: '[1]Simplification>'!$C$5
Name Cost_Of_debt: '[1]Simplify using Name'!$C$9
Name Cost_Of_equity: '[1]Simplify using Name'!$C$7
Name CostofDebt: '[1]Simplification>'!$C$6
Name Current_Sales: '[1]Simplify using Name'!$G$8
Name Debt_Funding: '[1]Simplify using Name'!$C$16
Name Debt_Value: '[1]Simplify using Name'!$C$14
Name DebtValue: '[1]Simplification>'!$C$9
Name Equity_Funding: '[1]Simplify using Name'!$C$15
Name Equity_Value: '[1]Simplify using Name'!$C$13
Name EquityValue: '[1]Simplification>'!$C$8
Name Gross_Margin: '[1]Simplify using Name'!$G$10
Name MarketReturn: '[1]Simplification>'!$C$4
Name Post_Tax_Cost_of_Debt: '[1]Simplify using Name'!$C$11
Name Riskfreerate: '[1]Simplification>'!$C$3
Name Sales_Growth: '[1]Simplify using Name'!$G$9
Name Taper_rate: 'DCF Model'!$C$21
Name Tax_rate: 'DCF Model'!$C$27
Name TAXRate: '[1]Simplification>'!$C$7
Name UPDATE: 'Data Sheet'!$E$1
Name UPDATE: '[2]Data Sheet'!$E$1

Sheet DCF Model
B2: Discounted Cashflow Model
B3: Financial Modelling Course
B6: Company Overview
B7: Indian Bank is a premier public sector financial institution in India headquartered in Chennai, Tamil Nadu
B9: Founded: March 5, 1907 (commenced business on August 15, 1907)
B10: Headquarters: Chennai, India
B11: Ownership: Majority owned by the Government of India.
B12: Leadership: Led by Managing Director and CEO Shri Binod Kumar.
B13: Operates over 6,000 domestic branches alongside international branches and an IBU in Gift City.
B16: Key Assumption And Methodology
B17: Parameter | C17: Value | D17: Rationale
B18: Valuation Date
B19: Projection Period
C20: 0.2 | D20: Based On management guidance
B21: Annual Growth Tapering | C21: 0.02
B23: Terminal Growth Rate | C23: 0.06 | D23: Conservative long term growth considering India's GDP and retail sector potential
B25: Risk Free Rate (RF) | C25: 0.065 | D25: India 10 year bond yield
B26: EquityRisk Premium (ERP) | C26: =12%-C25 -> 0.055 | D26: Exprcted return over RFR for equity investors
B27: Tax Rate | C27: 0.25 | D27: Effective Tax Rate based of historical performance
B30: Income Statement
B31: Particulars | C31: 43190 | D31: 43555 | E31: 43921 | F31: 44286 | G31: 44651 | H31: 45016 | I31: 45382 | J31: 45747 | K31: 46112 | L31: 46112
B32: Sales | C32: ='Data Sheet'!B17 -> 16039.22 | D32: ='Data Sheet'!C17 -> 17115.32 | E32: ='Data Sheet'!D17 -> 19182.06 | F32: ='Data Sheet'!E17 -> 21401.28 | G32: ='Data Sheet'!F17 -> 39108.08 | H32: ='Data Sheet'!G17 -> 38888.44 | I32: ='Data Sheet'!H17 -> 44985.16 | J32: ='Data Sheet'!I17 -> 55649.73 | ... L32: ='Data Sheet'!K17 -> 67504.09
B33: % Of growth | D33: =D32/C32-1 -> 0.067091791 | E33: =E32/D32-1 -> 0.1207538 | F33: =F32/E32-1 -> 0.11569248 | G33: =G32/F32-1 -> 0.82737107 | H33: =H32/G32-1 -> -0.0056162307 | I33: =I32/H32-1 -> 0.15677461 | J33: =J32/I32-1 -> 0.23706862 | K33: =K32/J32-1 -> 0.11481996 | L33: =L32/K32-1 -> 0.088083659
B34: COGS | C34: ='Data Sheet'!B21 -> 93.6 | D34: ='Data Sheet'!C21 -> 94.57 | E34: ='Data Sheet'!D21 -> 95.21 | F34: ='Data Sheet'!E21 -> 93.96 | G34: ='Data Sheet'!F21 -> 201.76 | H34: ='Data Sheet'!G21 -> 246.33 | I34: ='Data Sheet'!H21 -> 195.34 | J34: ='Data Sheet'!I21 -> 252.83 | ... L34: ='Data Sheet'!K21 -> 280.32
B35: % of revenue | C35: =C34/C32 -> 0.0058356953 | D35: =D34/D32 -> 0.0055254591 | E35: =E34/E32 -> 0.0049634919 | F35: =F34/F32 -> 0.0043903916 | G35: =G34/G32 -> 0.0051590362 | H35: =H34/H32 -> 0.0063342731 | I35: =I34/I32 -> 0.0043423209 | J35: =J34/J32 -> 0.0045432386 | ... L35: =L34/L32 -> 0.0041526373
B36: Gross Profit | C36: =C32-C34 -> 15945.62 | D36: =D32-D34 -> 17020.75 | E36: =E32-E34 -> 19086.85 | F36: =F32-F34 -> 21307.32 | G36: =G32-G34 -> 38906.32 | H36: =H32-H34 -> 38642.11 | I36: =I32-I34 -> 44789.82 | J36: =J32-J34 -> 55396.9 | ... L36: =L32-L34 -> 67223.77
B37: % Margin | C37: =C36/C32 -> 0.9941643 | D37: =D36/D32 -> 0.99447454 | E37: =E36/E32 -> 0.99503651 | F37: =F36/F32 -> 0.99560961 | G37: =G36/G32 -> 0.99484096 | H37: =H36/H32 -> 0.99366573 | I37: =I36/I32 -> 0.99565768 | J37: =J36/J32 -> 0.99545676 | ... L37: =L36/L32 -> 0.99584736
B38: Operating Expenses | C38: =SUM('Data Sheet'!B22:B24) -> 6049.97 | D38: =SUM('Data Sheet'!C22:C24) -> 6903.73 | E38: =SUM('Data Sheet'!D22:D24) -> 8193.58 | F38: =SUM('Data Sheet'!E22:E24) -> 9143.85 | G38: =SUM('Data Sheet'!F22:F24) -> 17827.2 | H38: =SUM('Data Sheet'!G22:G24) -> 20038.41 | I38: =SUM('Data Sheet'!H22:H24) -> 21381.45 | J38: =SUM('Data Sheet'!I22:I24) -> 20089.6 | ... L38: =SUM('Data Sheet'!K22:K24) -> 20429.8
B39: % Revenue | C39: =C38/C32 -> 0.37719852 | D39: =D38/D32 -> 0.40336552 | E39: =E38/E32 -> 0.42714807 | F39: =F38/F32 -> 0.42725715 | G39: =G38/G32 -> 0.45584442 | H39: =H38/H32 -> 0.51527935 | I39: =I38/I32 -> 0.47530008 | J39: =J38/J32 -> 0.36100085 | ... L39: =L38/L32 -> 0.30264537
B40: EBITDA | C40: =C36-C38 -> 9895.65 | D40: =D36-D38 -> 10117.02 | E40: =E36-E38 -> 10893.27 | F40: =F36-F38 -> 12163.47 | G40: =G36-G38 -> 21079.12 | H40: =H36-H38 -> 18603.7 | I40: =I36-I38 -> 23408.37 | J40: =J36-J38 -> 35307.3 | ... L40: =L36-L38 -> 46793.97
B41: % Revenue | C41: =C40/C32 -> 0.61696579 | D41: =D40/D32 -> 0.59110902 | E41: =E40/E32 -> 0.56788843 | F41: =F40/F32 -> 0.56835245 | G41: =G40/G32 -> 0.53899654 | H41: =H40/H32 -> 0.47838638 | I41: =I40/I32 -> 0.5203576 | J41: =J40/J32 -> 0.63445591 | ... L41: =L40/L32 -> 0.693202
B42: Depreciation | C42: ='Data Sheet'!B26 -> 166.24 | D42: ='Data Sheet'!C26 -> 236.84 | E42: ='Data Sheet'!D26 -> 259.29 | F42: ='Data Sheet'!E26 -> 314.01 | G42: ='Data Sheet'!F26 -> 636.9 | H42: ='Data Sheet'!G26 -> 600.86 | I42: ='Data Sheet'!H26 -> 532.39 | J42: ='Data Sheet'!I26 -> 531.14 | ... L42: ='Data Sheet'!K26 -> 608.86
B43: % Of Sales | C43: =C42/C32 -> 0.010364594 | D43: =D42/D32 -> 0.013837895 | E43: =E42/E32 -> 0.013517318 | F43: =F42/F32 -> 0.014672487 | G43: =G42/G32 -> 0.016285637 | H43: =H42/H32 -> 0.015450864 | I43: =I42/I32 -> 0.011834792 | J43: =J42/J32 -> 0.009544341 | ... L43: =L42/L32 -> 0.0090196016
B44: EBIT | C44: =C40-C42 -> 9729.41 | D44: =D40-D42 -> 9880.18 | E44: =E40-E42 -> 10633.98 | F44: =F40-F42 -> 11849.46 | G44: =G40-G42 -> 20442.22 | H44: =H40-H42 -> 18002.84 | I44: =I40-I42 -> 22875.98 | J44: =J40-J42 -> 34776.16 | ... L44: =L40-L42 -> 46185.11
B45: % Margin | C45: =C44/C32 -> 0.60660119 | D45: =D44/D32 -> 0.57727112 | E45: =E44/E32 -> 0.55437112 | F45: =F44/F32 -> 0.55367997 | G45: =G44/G32 -> 0.52271091 | H45: =H44/H32 -> 0.46293552 | I45: =I44/I32 -> 0.50852281 | J45: =J44/J32 -> 0.62491157 | ... L45: =L44/L32 -> 0.6841824
B46: Other Income | C46: ='Data Sheet'!B25 -> 2222.4 | D46: ='Data Sheet'!C25 -> 2416.59 | E46: ='Data Sheet'!D25 -> 1891.44 | F46: ='Data Sheet'!E25 -> 3325.5 | G46: ='Data Sheet'!F25 -> 6111.4 | H46: ='Data Sheet'!G25 -> 7379.71 | I46: ='Data Sheet'!H25 -> 7804.5 | J46: ='Data Sheet'!I25 -> 8581.95 | ... L46: ='Data Sheet'!K25 -> 10828.61
B47: Interest | C47: ='Data Sheet'!B27 -> 10891.46 | D47: ='Data Sheet'!C27 -> 10851.28 | E47: ='Data Sheet'!D27 -> 12166.75 | F47: ='Data Sheet'!E27 -> 13797.51 | G47: ='Data Sheet'!F27 -> 23438.8 | H47: ='Data Sheet'!G27 -> 22129.25 | I47: ='Data Sheet'!H27 -> 24717.29 | J47: ='Data Sheet'!I27 -> 32340.76 | ... L47: ='Data Sheet'!K27 -> 40538.66
B48: % Debt | C48: =C47/'Data Sheet'!B59 -> 0.055820169 | D48: =D47/'Data Sheet'!C59 -> 0.047588746 | E48: =E47/'Data Sheet'!D59 -> 0.047866982 | F48: =F47/'Data Sheet'!E59 -> 0.049098889 | G48: =G47/'Data Sheet'!F59 -> 0.041647316 | H48: =H47/'Data Sheet'!G59 -> 0.036230632 | I48: =I47/'Data Sheet'!H59 -> 0.038427688 | J48: =J47/'Data Sheet'!I59 -> 0.045480163 | ... L48: =L47/'Data Sheet'!K59 -> 0.046358476
B49: PBT | C49: =C44+C46-C47 -> 1060.35 | D49: =D44+D46-D47 -> 1445.49 | E49: =E44+E46-E47 -> 358.67 | F49: =F44+F46-F47 -> 1377.45 | G49: =G44+G46-G47 -> 3114.82 | H49: =H44+H46-H47 -> 3253.3 | I49: =I44+I46-I47 -> 5963.19 | J49: =J44+J46-J47 -> 11017.35 | ... L49: =L44+L46-L47 -> 16475.06
B50: % Revenue | C50: =C49/C32 -> 0.066109823 | D50: =D49/D32 -> 0.084455914 | E50: =E49/E32 -> 0.0186982 | F50: =F49/F32 -> 0.064362973 | G50: =G49/G32 -> 0.079646457 | H50: =H49/H32 -> 0.083657251 | I50: =I49/I32 -> 0.13255905 | J50: =J49/J32 -> 0.1979767 | ... L50: =L49/L32 -> 0.24406017
B51: Tax | C51: ='Data Sheet'!B29 -> -352.56 | D51: ='Data Sheet'!C29 -> 182.57 | E51: ='Data Sheet'!D29 -> 37.74 | F51: ='Data Sheet'!E29 -> 619.37 | G51: ='Data Sheet'!F29 -> 99.1 | H51: ='Data Sheet'!G29 -> -740.59 | I51: ='Data Sheet'!H29 -> 632.71 | J51: ='Data Sheet'!I29 -> 2888.2 | ... L51: ='Data Sheet'!K29 -> 4248.07
B52: % Revenue | C52: =C51/C49 -> -0.33249399 | D52: =D51/D49 -> 0.12630319 | E52: =E51/E49 -> 0.10522207 | F52: =F51/F49 -> 0.44964972 | G52: =G51/G49 -> 0.031815643 | H52: =H51/H49 -> -0.2276427 | I52: =I51/I49 -> 0.10610261 | J52: =J51/J49 -> 0.26215015 | ... L52: =L51/L49 -> 0.25784853
B53: Net Profit | C53: =C49-C51 -> 1412.91 | D53: =D49-D51 -> 1262.92 | E53: =E49-E51 -> 320.93 | F53: =F49-F51 -> 758.08 | G53: =G49-G51 -> 3015.72 | H53: =H49-H51 -> 3993.89 | I53: =I49-I51 -> 5330.48 | J53: =J49-J51 -> 8129.15 | ... L53: =L49-L51 -> 12226.99
B54: % Revenue | C54: =C53/C32 -> 0.088090942 | D54: =D53/D32 -> 0.073788863 | E54: =E53/E32 -> 0.016730737 | F54: =F53/F32 -> 0.03542218 | G54: =G53/G32 -> 0.077112453 | H54: =H53/H32 -> 0.10270121 | I54: =I53/I32 -> 0.11849419 | J54: =J53/J32 -> 0.14607708 | ... L54: =L53/L32 -> 0.18112962
B57: Balance Sheet
B58: Particulars | C58: 43190 | D58: 43555 | E58: 43921 | F58: 44286 | G58: 44651 | H58: 45016 | I58: 45382 | J58: 45747 | K58: 46112 | L58: 46112
B59: Equity Share capital | C59: ='Data Sheet'!B57 -> 480.29 | D59: ='Data Sheet'!C57 -> 480.29 | E59: ='Data Sheet'!D57 -> 480.29 | F59: ='Data Sheet'!E57 -> 608.8 | G59: ='Data Sheet'!F57 -> 1129.37 | H59: ='Data Sheet'!G57 -> 1245.44 | I59: ='Data Sheet'!H57 -> 1245.44 | J59: ='Data Sheet'!I57 -> 1346.96 | ... L59: ='Data Sheet'!K57 -> 1346.96
B60: Reserves | C60: ='Data Sheet'!B58 -> 16953.55 | D60: ='Data Sheet'!C58 -> 18235.15 | E60: ='Data Sheet'!D58 -> 19235.17 | F60: ='Data Sheet'!E58 -> 22158.78 | G60: ='Data Sheet'!F58 -> 38328.7 | H60: ='Data Sheet'!G58 -> 43706.49 | I60: ='Data Sheet'!H58 -> 48261.38 | J60: ='Data Sheet'!I58 -> 58901.24 | ... L60: ='Data Sheet'!K58 -> 78695.92
B61: Borrowings | C61: ='Data Sheet'!B59 -> 195116.93 | D61: ='Data Sheet'!C59 -> 228021.98 | E61: ='Data Sheet'!D59 -> 254178.34 | F61: ='Data Sheet'!E59 -> 281014.71 | G61: ='Data Sheet'!F59 -> 562792.57 | H61: ='Data Sheet'!G59 -> 610788.4 | I61: ='Data Sheet'!H59 -> 643215.65 | J61: ='Data Sheet'!I59 -> 711095.95 | ... L61: ='Data Sheet'!K59 -> 874460.58
B62: Other Liabilities | C62: ='Data Sheet'!B60 -> 5956.67 | D62: ='Data Sheet'!C60 -> 6243.99 | E62: ='Data Sheet'!D60 -> 6494.48 | F62: ='Data Sheet'!E60 -> 6358.67 | G62: ='Data Sheet'!F60 -> 23284.53 | H62: ='Data Sheet'!G60 -> 18356.1 | I62: ='Data Sheet'!H60 -> 20611.53 | J62: ='Data Sheet'!I60 -> 24364.67 | ... L62: ='Data Sheet'!K60 -> 37049.33
B63: Total | C63: =SUM(C59:C62) -> 218507.44 | D63: =SUM(D59:D62) -> 252981.41 | E63: =SUM(E59:E62) -> 280388.28 | F63: =SUM(F59:F62) -> 310140.96 | G63: =SUM(G59:G62) -> 625535.17 | H63: =SUM(H59:H62) -> 674096.43 | I63: =SUM(I59:I62) -> 713334 | J63: =SUM(J59:J62) -> 795708.82 | ... L63: =SUM(L59:L62) -> 991552.79
B64: Net Block | C64: ='Data Sheet'!B62 -> 3436.04 | D64: ='Data Sheet'!C62 -> 3421.47 | E64: ='Data Sheet'!D62 -> 3964.23 | F64: ='Data Sheet'!E62 -> 3898.3 | G64: ='Data Sheet'!F62 -> 7392.13 | H64: ='Data Sheet'!G62 -> 7693.78 | I64: ='Data Sheet'!H62 -> 7471.6 | J64: ='Data Sheet'!I62 -> 7537.62 | ... L64: ='Data Sheet'!K62 -> 8674
B65: Capital Work in Progress | C65: ='Data Sheet'!B63 -> 10.64 | D65: ='Data Sheet'!C63 -> 0.61 | E65: ='Data Sheet'!D63 -> 0.76 | F65: ='Data Sheet'!E63 -> 0.78 | G65: ='Data Sheet'!F63 -> 0.43 | H65: ='Data Sheet'!G63 -> 5.13 | I65: ='Data Sheet'!H63 -> 9.07 | J65: ='Data Sheet'!I63 -> 2.28 | ... L65: ='Data Sheet'!K63 -> 2.81
B66: Investments | C66: ='Data Sheet'!B64 -> 67781.19 | D66: ='Data Sheet'!C64 -> 71619.14 | E66: ='Data Sheet'!D64 -> 65271.55 | F66: ='Data Sheet'!E64 -> 81871.16 | G66: ='Data Sheet'!F64 -> 178292.44 | H66: ='Data Sheet'!G64 -> 176501.61 | I66: ='Data Sheet'!H64 -> 188366.28 | J66: ='Data Sheet'!I64 -> 215241.82 | ... L66: ='Data Sheet'!K64 -> 247682.04
B67: Other Assets | C67: 147279.57 | D67: 177940.19 | E67: 211151.74 | F67: 224370.72 | G67: 439850.17 | H67: 489895.91 | I67: 517487.05 | J67: 572927.1 | K67: 639760.41 | L67: 735193.94
B68: Total | C68: =SUM(C64:C68) -> 218507.44 | D68: =SUM(D64:D68) -> 252981.41 | E68: =SUM(E64:E68) -> 280388.28 | F68: =SUM(F64:F68) -> 310140.96 | G68: =SUM(G64:G68) -> 625535.17 | H68: =SUM(H64:H68) -> 674096.43 | I68: =SUM(I64:I68) -> 713334 | J68: =SUM(J64:J68) -> 795708.82 | ... L68: =SUM(L64:L68) -> 991552.79
B72: Revenue Projection And Growth Assumption
B73: Year | C73: 46112 | D73: 46477 | E73: 46843 | F73: 47208 | G73: 47573 | H73: 47938 | I73: 48304 | J73: 48669 | K73: 49034 | L73: 49399
B74: Revenue Growth% | C74: {=CHOOSE(D76,C77:L77,C78:L78,C79:L79)} -> 0.2 | D74: 0.18 | E74: 0.16 | F74: 0.14 | G74: 0.12 | H74: 0.1 | I74: 0.08 | J74: 0.06 | K74: 0.04 | L74: 0.02
B75: Revenue in (Crs) | C75: =L32*(1+C74) -> 81004.908 | D75: =C75*(1+D74) -> 95585.791 | E75: =D75*(1+E74) -> 110879.52 | F75: =E75*(1+F74) -> 126402.65 | G75: =F75*(1+G74) -> 141570.97 | H75: =G75*(1+H74) -> 155728.07 | I75: =H75*(1+I74) -> 168186.31 | J75: =I75*(1+J74) -> 178277.49 | K75: =J75*(1+K74) -> 185408.59 | L75: =K75*(1+L74) -> 189116.76
B76: Chosen Scenarios | C76: Base Case | D76: =MATCH(C76,B77:B79,0) -> 1
B77: Base Case | C77: =C20 -> 0.2 | D77: =C77-Taper_rate -> 0.18 | E77: =D77-Taper_rate -> 0.16 | F77: =E77-Taper_rate -> 0.14 | G77: =F77-Taper_rate -> 0.12 | H77: =G77-Taper_rate -> 0.1 | I77: =H77-Taper_rate -> 0.08 | J77: =I77-Taper_rate -> 0.06 | K77: =J77-Taper_rate -> 0.04 | L77: =K77-Taper_rate -> 0.02
B78: Best Case | C78: =C77+5% -> 0.25 | D78: =C78-Taper_rate -> 0.23 | E78: =D78-Taper_rate -> 0.21 | F78: =E78-Taper_rate -> 0.19 | G78: =F78-Taper_rate -> 0.17 | H78: =G78-Taper_rate -> 0.15 | I78: =H78-Taper_rate -> 0.13 | J78: =I78-Taper_rate -> 0.11 | K78: =J78-Taper_rate -> 0.09 | L78: =K78-Taper_rate -> 0.07
B79: Worst Case | C79: =C77-5% -> 0.15 | D79: =C79-Taper_rate -> 0.13 | E79: =D79-Taper_rate -> 0.11 | F79: =E79-Taper_rate -> 0.09 | G79: =F79-Taper_rate -> 0.07 | H79: =G79-Taper_rate -> 0.05 | I79: =H79-Taper_rate -> 0.03 | J79: =I79-Taper_rate -> 0.01 | K79: =J79-Taper_rate -> -0.01 | L79: =K79-Taper_rate -> -0.03
B82: Free Cash flow Projection (Rs Crs)
B83: Particulars | C83: 46112 | D83: 46477 | E83: 46843 | F83: 47208 | G83: 47573 | H83: 47938 | I83: 48304 | J83: 48669 | K83: 49034 | L83: 49399
B84: Revenue | C84: =C75 -> 81004.908 | D84: =D75 -> 95585.791 | E84: =E75 -> 110879.52 | F84: =F75 -> 126402.65 | G84: =G75 -> 141570.97 | H84: =H75 -> 155728.07 | I84: =I75 -> 168186.31 | J84: =J75 -> 178277.49 | ... L84: =L75 -> 189116.76
B85: EBITDA Margin% | C85: =L41 -> 0.693202 | D85: =C85 -> 0.693202 | E85: =D85 -> 0.693202 | F85: =E85 -> 0.693202 | G85: =F85 -> 0.693202 | H85: =G85 -> 0.693202 | I85: =H85 -> 0.693202 | J85: =I85 -> 0.693202 | K85: =J85 -> 0.693202 | L85: =K85 -> 0.693202
B86: EBITDA | C86: =C84*C85 -> 56152.764 | D86: =D84*D85 -> 66260.262 | E86: =E84*E85 -> 76861.903 | F86: =F84*F85 -> 87622.57 | G86: =G84*G85 -> 98137.278 | H86: =H84*H85 -> 107951.01 | I86: =I84*I85 -> 116587.09 | J86: =J84*J85 -> 123582.31 | ... L86: =L84*L85 -> 131096.12
B87: Less Depreciation | C87: =C84*AVERAGE($C$43:$L$43) -> 998.62089 | D87: =D84*AVERAGE($C$43:$L$43) -> 1178.3727 | E87: =E84*AVERAGE($C$43:$L$43) -> 1366.9123 | F87: =F84*AVERAGE($C$43:$L$43) -> 1558.28 | G87: =G84*AVERAGE($C$43:$L$43) -> 1745.2736 | H87: =H84*AVERAGE($C$43:$L$43) -> 1919.801 | I87: =I84*AVERAGE($C$43:$L$43) -> 2073.385 | J87: =J84*AVERAGE($C$43:$L$43) -> 2197.7881 | ... L87: =L84*AVERAGE($C$43:$L$43) -> 2331.4137
B88: EBIT | C88: =C86-C87 -> 55154.143 | D88: =D86-D87 -> 65081.889 | E88: =E86-E87 -> 75494.991 | F88: =F86-F87 -> 86064.29 | G88: =G86-G87 -> 96392.005 | H88: =H86-H87 -> 106031.21 | I88: =I86-I87 -> 114513.7 | J88: =J86-J87 -> 121384.52 | ... L88: =L86-L87 -> 128764.7
B89: Less Tax | C89: =C88*Tax_rate -> 13788.536 | D89: =D88*Tax_rate -> 16270.472 | E89: =E88*Tax_rate -> 18873.748 | F89: =F88*Tax_rate -> 21516.072 | G89: =G88*Tax_rate -> 24098.001 | H89: =H88*Tax_rate -> 26507.801 | I89: =I88*Tax_rate -> 28628.425 | J89: =J88*Tax_rate -> 30346.131 | ... L89: =L88*Tax_rate -> 32191.176
B90: NOPAT | C90: =C88-C89 -> 41365.607 | D90: =D88-D89 -> 48811.417 | E90: =E88-E89 -> 56621.243 | F90: =F88-F89 -> 64548.217 | G90: =G88-G89 -> 72294.003 | H90: =H88-H89 -> 79523.404 | I90: =I88-I89 -> 85885.276 | J90: =J88-J89 -> 91038.393 | ... L90: =L88-L89 -> 96573.527
B91: Add: Depreciation | C91: =C87 -> 998.62089 | D91: =D87 -> 1178.3727 | E91: =E87 -> 1366.9123 | F91: =F87 -> 1558.28 | G91: =G87 -> 1745.2736 | H91: =H87 -> 1919.801 | I91: =I87 -> 2073.385 | J91: =J87 -> 2197.7881 | ... L91: =L87 -> 2331.4137
B92: Less: Reinvestment | C92: =C90*-50% -> -20682.804 | D92: =D90*-50% -> -24405.708 | E92: =E90*-50% -> -28310.622 | F92: =F90*-50% -> -32274.109 | G92: =G90*-50% -> -36147.002 | H92: =H90*-50% -> -39761.702 | I92: =I90*-50% -> -42942.638 | J92: =J90*-50% -> -45519.196 | ... L92: =L90*-50% -> -48286.763
B93: Free Cash flow to firm | C93: =SUM(C90:C92) -> 21681.425 | D93: =SUM(D90:D92) -> 25584.081 | E93: =SUM(E90:E92) -> 29677.534 | F93: =SUM(F90:F92) -> 33832.389 | G93: =SUM(G90:G92) -> 37892.275 | H93: =SUM(H90:H92) -> 41681.503 | I93: =SUM(I90:I92) -> 45016.023 | J93: =SUM(J90:J92) -> 47716.984 | ... L93: =SUM(L90:L92) -> 50618.177
B97: WACC Calculation
B99: Target Capital Structure
B100: Proportion Of Debt | C100: =Comps!F19 -> 0.45101185
B101: Proportion Of Equity | C101: =Comps!E19 -> 0.82163766
B102: Current Capital Structure
B103: Market Cap | C103: =Comps!C9 -> 115792
B104: Tota Debt | C104: =Comps!D9 -> 46807
B105: Debt/Equity | C105: =C104/C103 -> 0.40423345
B106: Cost Of Debt
B107: Pre-tax cost of debt | C107: 0.07
B108: tax Rate | C108: {=Tax_rate} -> 0.25
B109: After Tax Cost of Debt | C109: =C107*(1-C108) -> 0.0525
B110: Cost Of Equity
B111: Risk Free Rate | C111: =C25 -> 0.065
B112: Equity Risk Premium | C112: =C26 -> 0.055
B113: Levered Equity Beta | C113: =Comps!I19*(1+'DCF Model'!C105*(1-Tax_rate)) -> 0.61476001
B114: Cost Of Equity | C114: =C111+C113*C112 -> 0.0988118
B115: WACC | C115: =(C114*C101)+(C109*C100) -> 0.10486562
B119: Terminal Value
B121: Terminal Year FCF (Fy30) | C121: =L93 -> 50618.177
B122: Terminal Growth Rate | C122: =C23 -> 0.06
B123: Terminal Value = FCF*(1+G) / (WACC-G)
B124: Terminal Value | C124: =C121*(1+C122)/(C115-C122) -> 1195910.6
B126: Present Value Calculation
...

Sheet Comps
B3: Comps Data
B4: Name | C4: Mar Cap ₹ Cr | D4: Debt ₹ Cr | E4: Debt / Eq | F4: Sales ₹ Cr | G4: Beta | H4: Cash & Equivalents ₹ Cr
B5: SBI | C5: 930400 | D5: 777302 | E5: 11.08 | F5: 136240.49 | G5: 1.05 | H5: 212013.35
B6: Union Bank | C6: 139893 | D6: 77798 | E6: 9.74 | F6: 27427.1 | G6: 1.42 | H6: 43255.93
B7: Punjab National Bank | C7: 133145 | D7: 107558 | E7: 11.79 | F7: 33589.17 | G7: 1.24 | H7: 71273.23
B8: Bank of Baroda | C8: 122587 | D8: 156357.45 | E8: 10.89 | F8: 35114.52 | G8: 1.26 | H8: 50665.14
B9: Indian Bank | C9: 115792 | D9: 46807 | E9: 10.64 | F9: 18095.14 | G9: 1.33 | H9: 31796
B11: Industry Beta
B13: Name | C13: Equit Value | D13: Total Debt | E13: Debt/Equity | F13: Debt /Capital | G13: Tax Rate % | H13: Levered Beta | I13: Unlivered Beta
B14: SBI | C14: =C5 -> 930400 | D14: =D5 -> 777302 | E14: =D14/C14 -> 0.83544927 | F14: =D14/(C14+D14) -> 0.45517426 | G14: =Tax_rate -> 0.25 | H14: =G5 -> 1.05 | I14: =H14/(1+E14)*(1-G14) -> 0.42905027
B15: Union Bank | C15: =C6 -> 139893 | D15: =D6 -> 77798 | E15: =D15/C15 -> 0.55612504 | F15: =D15/(C15+D15) -> 0.35737812 | G15: =Tax_rate -> 0.25 | H15: =G6 -> 1.42 | I15: =H15/(1+E15)*(1-G15) -> 0.6843923
B16: Punjab National Bank | C16: =C7 -> 133145 | D16: =D7 -> 107558 | E16: =D16/C16 -> 0.80782605 | F16: =D16/(C16+D16) -> 0.44684944 | G16: =Tax_rate -> 0.25 | H16: =G7 -> 1.24 | I16: =H16/(1+E16)*(1-G16) -> 0.51443002
B17: Bank of Baroda | C17: =C8 -> 122587 | D17: =D8 -> 156357.45 | E17: =D17/C17 -> 1.2754815 | F17: =D17/(C17+D17) -> 0.56053257 | G17: =Tax_rate -> 0.25 | H17: =G8 -> 1.26 | I17: =H17/(1+E17)*(1-G17) -> 0.41529672
B18: Average | E18: =AVERAGE(E14:E17) -> 0.86872046 | F18: =AVERAGE(F14:F17) -> 0.4549836 | G18: =AVERAGE(G14:G17) -> 0.25 | H18: =AVERAGE(H14:H17) -> 1.2425 | I18: =AVERAGE(I14:I17) -> 0.51079233
B19: Median | E19: =MEDIAN(E14:E17) -> 0.82163766 | F19: =MEDIAN(F14:F17) -> 0.45101185 | G19: =MEDIAN(G14:G17) -> 0.25 | H19: =MEDIAN(H14:H17) -> 1.25 | I19: =MEDIAN(I14:I17) -> 0.47174015

Sheet Data Sheet
A1: COMPANY NAME | B1: INDIAN BANK | E1: =IF(B2<>B3, "A NEW VERSION OF THE WORKSHEET IS AVAILABLE", "")
A2: LATEST VERSION | B2: 2.1 | E2: PLEASE DO NOT MAKE ANY CHANGES TO THIS SHEET
A3: CURRENT VERSION | B3: 2.1
B4: ='Data Sheet'!B1&" -" -> INDIAN BANK -
A5: META
A6: Number of shares | B6: =IF(B9>0, B9/B8, 0) -> 134.69635
A7: Face Value | B7: 10
A8: Current Price | B8: 857.05 | C8: =IFERROR('Data Sheet'!C18,'Data Sheet'!C20:C22)*-1 -> 0
A9: Market Capitalization | B9: 115441.51
A15: PROFIT & LOSS
A16: Report Date | B16: 42825 | C16: 43190 | D16: 43555 | E16: 43921 | F16: 44286 | G16: 44651 | H16: 45016 | I16: 45382 | J16: 45747 | K16: 46112
A17: Sales | B17: 16039.22 | C17: 17115.32 | D17: 19182.06 | E17: 21401.28 | F17: 39108.08 | G17: 38888.44 | H17: 44985.16 | I17: 55649.73 | J17: 62039.43 | K17: 67504.09
A18: Raw Material Cost
A19: Change in Inventory
A20: Power and Fuel
A21: Other Mfr. Exp | B21: 93.6 | C21: 94.57 | D21: 95.21 | E21: 93.96 | F21: 201.76 | G21: 246.33 | H21: 195.34 | I21: 252.83 | J21: 274.02 | K21: 280.32
A22: Employee Cost | B22: 1996.2 | C22: 2105.54 | D22: 2228.71 | E22: 2479.28 | F22: 6412.39 | G22: 6739.61 | H22: 7580.41 | I22: 9322.06 | J22: 9977.08 | K22: 10883.62
A23: Selling and admin | B23: 607.15 | C23: 640.96 | D23: 706.05 | E23: 739.22 | F23: 1573.52 | G23: 1652.98 | H23: 1807.53 | I23: 1816.52 | J23: 1975.06 | K23: 2253.58
A24: Other Expenses | B24: 3446.62 | C24: 4157.23 | D24: 5258.82 | E24: 5925.35 | F24: 9841.29 | G24: 11645.82 | H24: 11993.51 | I24: 8951.02 | J24: 7592.02 | K24: 7292.6
A25: Other Income | B25: 2222.4 | C25: 2416.59 | D25: 1891.44 | E25: 3325.5 | F25: 6111.4 | G25: 7379.71 | H25: 7804.5 | I25: 8581.95 | J25: 10011.45 | K25: 10828.61
A26: Depreciation | B26: 166.24 | C26: 236.84 | D26: 259.29 | E26: 314.01 | F26: 636.9 | G26: 600.86 | H26: 532.39 | I26: 531.14 | J26: 542.94 | K26: 608.86
A27: Interest | B27: 10891.46 | C27: 10851.28 | D27: 12166.75 | E27: 13797.51 | F27: 23438.8 | G27: 22129.25 | H27: 24717.29 | I27: 32340.76 | J27: 36826.25 | K27: 40538.66
A28: Profit before tax | B28: 1060.35 | C28: 1445.49 | D28: 358.67 | E28: 1377.45 | F28: 3114.82 | G28: 3253.3 | H28: 5963.19 | I28: 11017.35 | J28: 14863.51 | K28: 16475.06
A29: Tax | B29: -352.56 | C29: 182.57 | D29: 37.74 | E29: 619.37 | F29: 99.1 | G29: -740.59 | H29: 632.71 | I29: 2888.2 | J29: 3868.64 | K29: 4248.07
A30: Net profit | B30: 1453.06 | C30: 1310.54 | D30: 380.13 | E30: 861.34 | F30: 3149.15 | G30: 4141.81 | H30: 5572.31 | I30: 8419.41 | J30: 11261.47 | K30: 11704.28
A31: Dividend Amount | B31: 288.17 | F31: 225.87 | G31: 809.54 | H31: 1071.08 | I31: 1616.35 | J31: 2188.81 | K31: 2458.2
A40: Quarters
A41: Report Date | B41: 45382 | C41: 45473 | D41: 45565 | E41: 45657 | F41: 45747 | G41: 45838 | H41: 45930 | I41: 46022 | J41: 46112 | K41: 46203
A42: Sales | B42: 14633.41 | C42: 15040.63 | D42: 15369.01 | E42: 15770.16 | F42: 15859.63 | G42: 16285.1 | H42: 16628.28 | I42: 17102.21 | J42: 17488.5 | K42: 18095.14
A43: Expenses | B43: 5378.16 | C43: 4994.32 | D43: 5143.73 | E43: 5101.71 | F43: 5097.49 | G43: 4880.15 | H43: 5108.39 | I43: 5492.5 | J43: 5811.46 | K43: 5946.06
A44: Other Income | B44: 2432.08 | C44: 2077.13 | D44: 2602.21 | E44: 2397.38 | F44: 2934.73 | G44: 1853.91 | H44: 2642.81 | I44: 2792.57 | J44: 2772.73 | K44: 2902.24
A45: Depreciation
A46: Interest | B46: 8609.13 | C46: 8860.51 | D46: 9153.5 | E46: 9345.18 | F46: 9467.06 | G46: 9924.09 | H46: 10039.71 | I46: 10202.9 | J46: 10371.96 | K46: 10656.86
A47: Profit before tax | B47: 3078.2 | C47: 3262.93 | D47: 3673.99 | E47: 3720.65 | F47: 4229.81 | G47: 3334.77 | H47: 4122.99 | I47: 4199.38 | J47: 4077.81 | K47: 4394.46
A48: Tax | B48: 817.89 | C48: 845.63 | D48: 933.96 | E48: 844.5 | F48: 1268.42 | G48: 1116.26 | H48: 1082.46 | I48: 1113.22 | J48: 962.61 | K48: 1094.98
A49: Net profit | B49: 2295.61 | C49: 2570.4 | D49: 2799.7 | E49: 2909.73 | F49: 2981.64 | G49: 2276.37 | H49: 3107.97 | I49: 3146.88 | J49: 3173.05 | K49: 3356.63
A50: Operating Profit | B50: 9255.25 | C50: 10046.31 | D50: 10225.28 | E50: 10668.45 | F50: 10762.14 | G50: 11404.95 | H50: 11519.89 | I50: 11609.71 | J50: 11677.04 | K50: 12149.08
A51: EBITDA | B51: 16892.02 | C51: 20164.6 | D51: 19850 | E51: 20404 | F51: 22268 | G51: 23828 | H51: 22359 | I51: 18164 | J51: 17822 | K51: 22113
A55: BALANCE SHEET
A56: Report Date | B56: 42825 | C56: 43190 | D56: 43555 | E56: 43921 | F56: 44286 | G56: 44651 | H56: 45016 | I56: 45382 | J56: 45747 | K56: 46112
A57: Equity Share Capital | B57: 480.29 | C57: 480.29 | D57: 480.29 | E57: 608.8 | F57: 1129.37 | G57: 1245.44 | H57: 1245.44 | I57: 1346.96 | J57: 1346.96 | K57: 1346.96
A58: Reserves | B58: 16953.55 | C58: 18235.15 | D58: 19235.17 | E58: 22158.78 | F58: 38328.7 | G58: 43706.49 | H58: 48261.38 | I58: 58901.24 | J58: 70165.95 | K58: 78695.92
A59: Borrowings | B59: 195116.93 | C59: 228021.98 | D59: 254178.34 | E59: 281014.71 | F59: 562792.57 | G59: 610788.4 | H59: 643215.65 | I59: 711095.95 | J59: 778650.62 | K59: 874460.58
A60: Other Liabilities | B60: 5956.67 | C60: 6243.99 | D60: 6494.48 | E60: 6358.67 | F60: 23284.53 | G60: 18356.1 | H60: 20611.53 | I60: 24364.67 | J60: 26875.07 | K60: 37049.33
A61: Total | B61: 218507.44 | C61: 252981.41 | D61: 280388.28 | E61: 310140.96 | F61: 625535.17 | G61: 674096.43 | H61: 713334 | I61: 795708.82 | J61: 877038.6 | K61: 991552.79
A62: Net Block | B62: 3436.04 | C62: 3421.47 | D62: 3964.23 | E62: 3898.3 | F62: 7392.13 | G62: 7693.78 | H62: 7471.6 | I62: 7537.62 | J62: 8854.38 | K62: 8674
A63: Capital Work in Progress | B63: 10.64 | C63: 0.61 | D63: 0.76 | E63: 0.78 | F63: 0.43 | G63: 5.13 | H63: 9.07 | I63: 2.28 | J63: 2.95 | K63: 2.81
A64: Investments | B64: 67781.19 | C64: 71619.14 | D64: 65271.55 | E64: 81871.16 | F64: 178292.44 | G64: 176501.61 | H64: 188366.28 | I64: 215241.82 | J64: 228420.86 | K64: 247682.04
A65: Other Assets | B65: 147279.57 | C65: 177940.19 | D65: 211151.74 | E65: 224370.72 | F65: 439850.17 | G65: 489895.91 | H65: 517487.05 | I65: 572927.1 | J65: 639760.41 | K65: 735193.94
A66: Total | B66: 218507.44 | C66: 252981.41 | D66: 280388.28 | E66: 310140.96 | F66: 625535.17 | G66: 674096.43 | H66: 713334 | I66: 795708.82 | J66: 877038.6 | K66: 991552.79
A67: Receivables
A68: Inventory
A69: Cash & Bank | B69: 5588.7 | C69: 10501.6 | D69: 11701.87 | E69: 5736.12 | F69: 27545.18 | G69: 58554.66 | H69: 32692.73 | I69: 32702.76 | J69: 31947.65 | K69: 34054.92
A70: No. of Equity Shares | B70: 480291651 | C70: 480291651 | D70: 480291651 | E70: 608800580 | F70: 1129366570 | G70: 1245441139 | H70: 1245441139 | I70: 1346963981 | J70: 1346963981 | K70: 1346963981
A71: New Bonus Shares
A72: Face value | B72: 10 | C72: 10 | D72: 10 | E72: 10 | F72: 10 | G72: 10 | H72: 10 | I72: 10 | J72: 10 | K72: 10
A80: CASH FLOW:
A81: Report Date | B81: 42825 | C81: 43190 | D81: 43555 | E81: 43921 | F81: 44286 | G81: 44651 | H81: 45016 | I81: 45382 | J81: 45747 | K81: 46112
A82: Cash from Operating Activity | B82: -10813.85 | C82: -3675.79 | D82: 6269.85 | E82: -8396.17 | F82: 17064.55 | G82: 28750.33 | H82: -27893.99 | I82: -8617.26 | J82: 17396.4 | K82: 18815.48
A83: Cash from Investing Activity | B83: -179.37 | C83: -214.38 | D83: -175.73 | E83: -247.37 | F83: 21232.98 | G83: -304.69 | H83: -313.98 | I83: -617.7 | J83: -348.4 | K83: -428.07
A84: Cash from Financing Activity | B84: 9040.86 | C84: 6776.44 | D84: 1000 | E84: 2552.42 | F84: 1865.55 | G84: 18.43 | H84: -1543.42 | I84: 1195.04 | J84: -4263.51 | K84: -7649.12
A85: Net Cash Flow | B85: -1952.36 | C85: 2886.27 | D85: 7094.12 | E85: -6091.12 | F85: 40163.08 | G85: 28464.07 | H85: -29751.39 | I85: -8039.92 | J85: 12784.49 | K85: 10738.29
A90: PRICE: | B90: 278.25 | C90: 299.8 | D90: 280.1 | E90: 43.1 | F90: 116.1 | G90: 153.9 | H90: 288.55 | I90: 520.7 | J90: 541.3 | K90: 845.7
A92: DERIVED:
A93: Adjusted Equity Shares in Cr | B93: 48.03 | C93: 48.03 | D93: 48.03 | E93: 60.88 | F93: 112.94 | G93: 124.54 | H93: 124.54 | I93: 134.7 | J93: 134.7 | K93: 134.7
